banquo/__init__.py
banquo/_banquo_impl.cpython-310-arm-linux-gnueabihf.so
banquo/_banquo_impl.pyi
banquo/core.py
banquo/expressions.py
banquo/operators.py
banquo/py.typed
banquo/trace.py
pybanquo-0.1.0.dist-info/METADATA
pybanquo-0.1.0.dist-info/WHEEL
pybanquo-0.1.0.dist-info/licenses/LICENSE
pybanquo-0.1.0.dist-info/RECORD
