Metadata-Version: 2.4
Name: pybanquo
Version: 0.1.0
Classifier: Programming Language :: Rust
Classifier: Programming Language :: Python :: 3.9
Classifier: Programming Language :: Python :: 3.10
Classifier: Programming Language :: Python :: 3.11
Classifier: Programming Language :: Python :: 3.12
Classifier: Programming Language :: Python :: Implementation :: CPython
Classifier: Programming Language :: Python :: Implementation :: PyPy
Requires-Dist: typing-extensions>=4.13.2
License-File: LICENSE
Summary: Python bindings for Banquo offline temporal logic monitor
Author-email: Quinn Thibeault <qthibeau@asu.edu>
Requires-Python: >=3.9
Project-URL: repository, https://github.com/cpslab-asu/banquo-python
